croco-0.0.2.dist-info/RECORD
croco-0.0.2.dist-info/top_level.txt
croco-0.0.2.dist-info/METADATA
croco-0.0.2.dist-info/DESCRIPTION.rst
croco-0.0.2.dist-info/metadata.json
croco-0.0.2.dist-info/WHEEL
croco/__init__.py
croco/_crocodile_billing.py
