Metadata-Version: 2.0
Name: croco
Version: 0.0.2
Summary: CrocoValidator validate Google or IOS's In-App Purchase in Python
Home-page: https://jochangmin@bitbucket.org/jochangmin/croco-validator.git
Author: Chang Min Jo (Anderson)
Author-email: a141890@{nospam}gmail.com
License: MIT
Download-URL: https://bitbucket.org/jochangmin/croco-validator/get/007176326994.zip
Platform: any
Classifier: Intended Audience :: Developers
Classifier: License :: OSI Approved :: MIT License
Classifier: Operating System :: OS Independent
Classifier: Programming Language :: Python
Classifier: Programming Language :: Python :: 2
Classifier: Programming Language :: Python :: 2.6
Classifier: Programming Language :: Python :: 2.7
Classifier: Programming Language :: Python :: 3
Classifier: Programming Language :: Python :: 3.1
Classifier: Programming Language :: Python :: 3.2
Classifier: Programming Language :: Python :: Implementation :: CPython
Classifier: Topic :: Database
Classifier: Topic :: Software Development :: Libraries :: Python Modules
Requires-Dist: pycrypto
